{"name":"CS6475 Final Project","tagline":"Timothy Rohr and David Whiskochil","body":"# The Goal of this project was to create an Anaglyph 360 Panorama. \r\n# Our Code can be found in the Github repository for our site. \r\n# Final Results\r\n`<a href=\"http://s492.photobucket.com/user/Foxtrot_Co/media/OMSCS/National%20Harbor%203.jpg.html\" target=\"_blank\"><img src=\"http://i492.photobucket.com/albums/rr290/Foxtrot_Co/OMSCS/National%20Harbor%203.jpg\" border=\"0\" alt=\" photo National Harbor 3.jpg\"/></a>`\r\n\r\n# Details about the project \r\n* This project was fun. ","google":"","note":"Don't delete this file! It's used internally to help with page regeneration."}